lvm_tools/__init__.py
lvm_tools/_version.py
lvm_tools/py.typed
lvm_tools/config/__init__.py
lvm_tools/config/data_config.py
lvm_tools/config/validation.py
lvm_tools/data/__init__.py
lvm_tools/data/coordinates.py
lvm_tools/data/helper.py
lvm_tools/data/tile.py
lvm_tools/fit_data/__init__.py
lvm_tools/fit_data/builder.py
lvm_tools/fit_data/clipping.py
lvm_tools/fit_data/filtering.py
lvm_tools/fit_data/fit_data.py
lvm_tools/fit_data/normalisation.py
lvm_tools/fit_data/processing.py
lvm_tools/physical_properties/__init__.py
lvm_tools/physical_properties/barycentric_corr.py
lvm_tools/utils/__init__.py
lvm_tools/utils/mask.py
lvm_tools-0.0.10.dist-info/METADATA
lvm_tools-0.0.10.dist-info/WHEEL
lvm_tools-0.0.10.dist-info/licenses/LICENSE
lvm_tools-0.0.10.dist-info/RECORD
