Metadata-Version: 2.4
Name: lvm_tools
Version: 0.0.10
Summary: Lazily read/encapsulate LVM DRP data in a modular way
Author-email: Tom Hilder <Thomas.Hilder@monash.edu>
License-File: LICENSE
Requires-Python: >=3.10
Requires-Dist: astropy>=6.0.0
Requires-Dist: dask>=2024.1.0
Requires-Dist: jax>=0.4.31
Requires-Dist: numpy>=2.0.0
Requires-Dist: scipy>=1.11.0
Requires-Dist: xarray>=2024.1.0
Provides-Extra: spectracles
Requires-Dist: spectracles>=0.5.1; (python_version >= '3.13') and extra == 'spectracles'
